odoo10_addon_pingen-10.0.1.0.0.99.dev5-py3.8-nspkg.pth
odoo/addons/pingen/README.rst
odoo/addons/pingen/__init__.py
odoo/addons/pingen/__manifest__.py
odoo/addons/pingen/data/pingen_data.xml
odoo/addons/pingen/i18n/fr.po
odoo/addons/pingen/i18n/pingen.pot
odoo/addons/pingen/models/__init__.py
odoo/addons/pingen/models/base_config_settings.py
odoo/addons/pingen/models/ir_attachment.py
odoo/addons/pingen/models/pingen.py
odoo/addons/pingen/models/pingen_document.py
odoo/addons/pingen/models/res_company.py
odoo/addons/pingen/security/ir.model.access.csv
odoo/addons/pingen/static/description/icon.png
odoo/addons/pingen/views/base_config_settings.xml
odoo/addons/pingen/views/ir_attachment_view.xml
odoo/addons/pingen/views/pingen_document_view.xml
odoo10_addon_pingen-10.0.1.0.0.99.dev5.dist-info/METADATA
odoo10_addon_pingen-10.0.1.0.0.99.dev5.dist-info/WHEEL
odoo10_addon_pingen-10.0.1.0.0.99.dev5.dist-info/namespace_packages.txt
odoo10_addon_pingen-10.0.1.0.0.99.dev5.dist-info/top_level.txt
odoo10_addon_pingen-10.0.1.0.0.99.dev5.dist-info/RECORD
